MANIFEST.in
README.md
setup.py
openbot_frontend/__init__.py
openbot_frontend/asset-manifest.json
openbot_frontend/favicon.ico
openbot_frontend/index.html
openbot_frontend/logo192.png
openbot_frontend/logo512.png
openbot_frontend/manifest.json
openbot_frontend/robots.txt
openbot_frontend.egg-info/PKG-INFO
openbot_frontend.egg-info/SOURCES.txt
openbot_frontend.egg-info/dependency_links.txt
openbot_frontend.egg-info/not-zip-safe
openbot_frontend.egg-info/top_level.txt
openbot_frontend/static/css/2.d5f8747c.chunk.css
openbot_frontend/static/css/2.d5f8747c.chunk.css.map
openbot_frontend/static/css/main.11870555.chunk.css
openbot_frontend/static/css/main.11870555.chunk.css.map
openbot_frontend/static/js/2.ea05dc24.chunk.js
openbot_frontend/static/js/2.ea05dc24.chunk.js.LICENSE.txt
openbot_frontend/static/js/2.ea05dc24.chunk.js.map
openbot_frontend/static/js/3.707a6c27.chunk.js
openbot_frontend/static/js/3.707a6c27.chunk.js.map
openbot_frontend/static/js/main.046d3013.chunk.js
openbot_frontend/static/js/main.046d3013.chunk.js.map
openbot_frontend/static/js/runtime-main.60e10ace.js
openbot_frontend/static/js/runtime-main.60e10ace.js.map