Metadata-Version: 1.0
Name: openbot-frontend
Version: 0.7.0
Summary: OpenBot Frontend package
Home-page: https://github.com/sanyatuning/OpenBot
Author: Balazs Sandor
Author-email: sanyatuning@gmail.com
License: MIT
Platform: UNKNOWN
